rraster/Raster.py
rraster/Rasterize.py
rraster/__init__.py
rraster/data/19990601_pr.tif
rraster/data/19990602_pr.tif
rraster/data/19990603_pr.tif
rraster/data/19990604_pr.tif
rraster/data/19990605_pr.tif
rraster/data/19990606_pr.tif
rraster/data/19990607_pr.tif
rraster/data/template.tif
RRaster-0.0.3.dist-info/LICENSE
RRaster-0.0.3.dist-info/METADATA
RRaster-0.0.3.dist-info/WHEEL
RRaster-0.0.3.dist-info/top_level.txt
RRaster-0.0.3.dist-info/RECORD
