Metadata-Version: 2.1
Name: RRaster
Version: 0.0.3
Summary: Rasterio function wrappers for simple raster processing in Python that mimics the R Raster syntax.
Home-page: https://github.com/colinbrust/RRaster
Author: Colin Brust
Author-email: colin.brust@gmail.com
License: UNKNOWN
Keywords: raster,rasterio,R,simplified
Platform: UNKNOWN
Requires-Python: >=3.6, <4
License-File: LICENSE
Requires-Dist: rasterio
Requires-Dist: numpy
Requires-Dist: matplotlib
Requires-Dist: geopandas
